quantalogic/__init__.py
quantalogic/agent.py
quantalogic/agent_config.py
quantalogic/agent_factory.py
quantalogic/coding_agent.py
quantalogic/config.py
quantalogic/console_print_events.py
quantalogic/console_print_token.py
quantalogic/create_custom_agent.py
quantalogic/docs_cli.py
quantalogic/event_emitter.py
quantalogic/flow/__init__.py
quantalogic/generative_model.py
quantalogic/get_model_info.py
quantalogic/interactive_text_editor.py
quantalogic/main.py
quantalogic/memory.py
quantalogic/model_info.py
quantalogic/model_info_list.py
quantalogic/model_info_litellm.py
quantalogic/model_names.py
quantalogic/prompts/chat_system_prompt.j2
quantalogic/prompts/code_2_system_prompt.j2
quantalogic/prompts/code_system_prompt.j2
quantalogic/prompts/doc_system_prompt.j2
quantalogic/prompts/legal_2_system_prompt.j2
quantalogic/prompts/legal_system_prompt.j2
quantalogic/prompts/memory_compaction_prompt.j2
quantalogic/prompts/observation_response_format.j2
quantalogic/prompts/repeated_tool_call_error.j2
quantalogic/prompts/system_prompt.j2
quantalogic/prompts/task_prompt.j2
quantalogic/prompts/task_summary_prompt.j2
quantalogic/prompts/tools_prompt.j2
quantalogic/prompts/variables_prompt.j2
quantalogic/prompts.py
quantalogic/quantlitellm.py
quantalogic/search_agent.py
quantalogic/server/__init__.py
quantalogic/server/agent_server.py
quantalogic/server/models.py
quantalogic/server/routes.py
quantalogic/server/state.py
quantalogic/server/static/js/event_visualizer.js
quantalogic/server/static/js/quantalogic.js
quantalogic/server/templates/index.html
quantalogic/task_file_reader.py
quantalogic/task_runner.py
quantalogic/tool_manager.py
quantalogic/tools/__init__.py
quantalogic/tools/action_gen.py
quantalogic/tools/action_gen_safe.py
quantalogic/tools/agent_tool.py
quantalogic/tools/composio/__init__.py
quantalogic/tools/composio/composio.py
quantalogic/tools/database/__init__.py
quantalogic/tools/database/generate_database_report_tool.py
quantalogic-0.93.dist-info/LICENSE
quantalogic-0.93.dist-info/METADATA
quantalogic-0.93.dist-info/WHEEL
quantalogic-0.93.dist-info/entry_points.txt
quantalogic-0.93.dist-info/RECORD
