Metadata-Version: 2.3
Name: quantalogic
Version: 0.93
Summary: QuantaLogic ReAct Agents
License: MIT
Author: Raphaël MANSUY
Author-email: raphael.mansuy@gmail.com
Requires-Python: >=3.10,<4.0
Classifier: License :: OSI Approved :: MIT License
Classifier: Programming Language :: Python :: 3
Classifier: Programming Language :: Python :: 3.10
Classifier: Programming Language :: Python :: 3.11
Classifier: Programming Language :: Python :: 3.12
Classifier: Programming Language :: Python :: 3.13
Requires-Dist: aiofiles (>=24.1.0,<25.0.0)
Requires-Dist: beautifulsoup4 (>=4.12.3,<5.0.0)
Requires-Dist: boto3 (>=1.34.0,<2.0.0)
Requires-Dist: botocore (>=1.29.123,<2.0.0)
Requires-Dist: click (>=8.1.8,<9.0.0)
Requires-Dist: duckduckgo-search (>=7.2.1,<8.0.0)
Requires-Dist: faker (>=36.1.1,<37.0.0)
Requires-Dist: fuzzywuzzy (>=0.18.0,<0.19.0)
Requires-Dist: google-search-results (>=2.4.2,<3.0.0)
Requires-Dist: html2text (>=2024.2.26,<2025.0.0)
Requires-Dist: instructor (>=1.7.2,<2.0.0)
Requires-Dist: jinja2 (>=3.1.5,<4.0.0)
Requires-Dist: litellm (>=1.63.14,<2.0.0)
Requires-Dist: loguru (>=0.7.3,<0.8.0)
Requires-Dist: markdownify (>=0.14.1,<0.15.0)
Requires-Dist: markitdown (>=0.0.1a3,<0.0.2)
Requires-Dist: networkx (>=3.2.1,<4.0.0)
Requires-Dist: openai (>=1.68.0,<2.0.0)
Requires-Dist: pathspec (>=0.12.1,<0.13.0)
Requires-Dist: prompt-toolkit (>=3.0.48,<4.0.0)
Requires-Dist: psutil (>=7.0.0,<8.0.0)
Requires-Dist: pydantic (>=2.10.4,<3.0.0)
Requires-Dist: pytest-asyncio (>=0.25.3,<0.26.0)
Requires-Dist: python-dotenv (>=1.0.1,<2.0.0)
Requires-Dist: quantalogic-flow (>=0.6.2,<0.7.0)
Requires-Dist: quantalogic-pythonbox (>=0.9.11)
Requires-Dist: quantalogic-toolbox (>=0.8.0)
Requires-Dist: requests (>=2.32.3,<3.0.0)
Requires-Dist: rich (>=13.9.4,<14.0.0)
Requires-Dist: serpapi (>=0.1.5,<0.2.0)
Requires-Dist: sqlalchemy (>=2.0.25,<3.0.0)
Requires-Dist: tenacity (>=9.0.0,<10.0.0)
Requires-Dist: tree-sitter (>=0.23.2,<0.24.0)
Requires-Dist: tree-sitter-c (>=0.23.4,<0.24.0)
Requires-Dist: tree-sitter-cpp (>=0.23.4,<0.24.0)
Requires-Dist: tree-sitter-go (>=0.23.4,<0.24.0)
Requires-Dist: tree-sitter-java (>=0.23.5,<0.24.0)
Requires-Dist: tree-sitter-javascript (>=0.23.1,<0.24.0)
Requires-Dist: tree-sitter-python (>=0.23.6,<0.24.0)
Requires-Dist: tree-sitter-rust (>=0.23.2,<0.24.0)
Requires-Dist: tree-sitter-scala (>=0.23.4,<0.24.0)
Requires-Dist: tree-sitter-typescript (>=0.23.2,<0.24.0)
Requires-Dist: types-pyyaml (>=6.0.12.20241230,<7.0.0.0)
Requires-Dist: typing-extensions (>=4.12.2,<5.0.0)
Project-URL: Documentation, https://github.com/quantalogic/quantalogic#readme
Project-URL: Homepage, https://github.com/quantalogic/quantalogic
Project-URL: Repository, https://github.com/quantalogic/quantalogic
